{
  "function_info": {
    "func_name": "handle_upload_notes",
    "file_path": "src/main_web.c",
    "start_line": 1,
    "end_line": 100,
    "code_snippet": "",
    "input": "用户ID、FTP主机"
  },
  "code_map": [
    {
      "function_name": "handle_upload_notes",
      "file_path": "src/main_web.c",
      "line_start": 316,
      "line_end": 325,
      "code_snippet": "static int handle_upload_notes(struct mg_connection* conn, void* cbdata) {\n    char user_id_str[32], host[256];\n    if (!get_param(conn, \"user_id\", user_id_str, sizeof(user_id_str)) ||\n        !get_param(conn, \"host\", host, sizeof(host))) {\n        send_json(conn, 400, \"Missing parameters\", NULL);\n        return 200;\n    }\n\n    int user_id = atoi(user_id_str);\n    int rc = note_upload_notes_to_ftp(user_id, host, \"/\");",
      "is_entry_point": true,
      "taint_source": "get_param(conn, \"host\", host, sizeof(host))",
      "taint_path": "外部输入host参数"
    },
    {
      "function_name": "get_param",
      "file_path": "src/main_web.c",
      "line_start": 24,
      "line_end": 40,
      "code_snippet": "static const char* get_param(struct mg_connection* conn, const char* name, char* buf, size_t buf_size) {\n    const struct mg_request_info* ri = mg_get_request_info(conn);\n\n    // 先尝试从 query_string 获取 (GET 请求)\n    if (ri->query_string) {\n        int len = mg_get_var(ri->query_string, strlen(ri->query_string), name, buf, buf_size);\n        if (len > 0) return buf;\n    }\n\n    // 尝试从 POST 数据获取\n    // 读取 POST 数据\n    char post_data[MAX_POST_DATA];\n    int post_len = mg_read(conn, post_data, sizeof(post_data) - 1);\n    if (post_len > 0) {\n        post_data[post_len] = '\\0';\n        int len = mg_get_var(post_data, post_len, name, buf, buf_size);\n        if (len > 0) return buf;\n    }\n\n    return NULL;\n}",
      "is_entry_point": false,
      "taint_source": "mg_get_var, mg_read",
      "taint_path": "HTTP请求参数获取"
    },
    {
      "function_name": "note_upload_notes_to_ftp",
      "file_path": "src/note_logic.c",
      "line_start": 171,
      "line_end": 189,
      "code_snippet": "int note_upload_notes_to_ftp(int user_id, const char* host, const char* path) {\n    FtpConfig config;\n    int rc = db_ftp_config_get_by_user(user_id, &config);\n    if (rc != 0) {\n        return -1;\n    }\n\n    // 漏洞点：这里用system拼接IP做ping测试\n    // 攻击者可以注入命令\n    char cmd[512];\n    snprintf(cmd, sizeof(cmd), \"ping -c 1 %s > /dev/null 2>&1 && echo OK\", host);\n\n    // 命令注入漏洞点\n    int ping_result = system(cmd);\n\n    if (ping_result != 0) {\n        return -2;\n    }\n\n    return 0;\n}",
      "is_entry_point": false,
      "taint_source": "host参数",
      "taint_path": "污染数据通过snprintf拼接进入system命令执行"
    }
  ],
  "audit_results": [],
  "exploit_results": [],
  "_checkpoint_meta": {
    "saved_at": "2026-03-19T03:41:09.649717",
    "func_name": "handle_upload_notes",
    "file_path": "src/main_web.c"
  }
}